azblob/__init__.py
azblob/__main__.py
azblob/auxilliaries.py
azblob/ops.py
azblob-0.2.0.dist-info/METADATA
azblob-0.2.0.dist-info/RECORD
azblob-0.2.0.dist-info/WHEEL
azblob-0.2.0.dist-info/entry_points.txt
azblob-0.2.0.dist-info/top_level.txt
