Metadata-Version: 2.1
Name: azblob
Version: 0.2.0
Summary: Download Azure blobs.
Home-page: https://github.com/plang85/azblob
Author: Philipp Lang
License: MIT License
Platform: UNKNOWN
Classifier: Programming Language :: Python :: 3.6
Classifier: License :: OSI Approved :: MIT License
Classifier: Topic :: Software Development
Provides-Extra: dev
Requires-Dist: azure-storage-blob (>=1.3.0)
Requires-Dist: azure-storage-file (>=1.3.0)
Requires-Dist: tqdm (>=4.0.0)
Requires-Dist: tabulate (>=0.8.2)
Provides-Extra: dev
Requires-Dist: black; extra == 'dev'
Requires-Dist: twine; extra == 'dev'
